dataframetodb/__init__.py
dataframetodb/column.py
dataframetodb/table.py
dataframetodb/utils.py
dataframetodb-1.0.dist-info/LICENSE.md
dataframetodb-1.0.dist-info/LICENSE.txt
dataframetodb-1.0.dist-info/METADATA
dataframetodb-1.0.dist-info/WHEEL
dataframetodb-1.0.dist-info/top_level.txt
dataframetodb-1.0.dist-info/RECORD
