Metadata-Version: 2.1
Name: dataframetodb
Version: 1.0
Summary: A conector for save dataframe to db and others utils with sqlalchemy
Home-page: https://github.com/juanretamales/DataframeToDB
Author: Juan Retamales
Author-email: jua.retamales@gmail.com
License: UNKNOWN
Download-URL: https://github.com/juanretamales/DataframeToDB/tarball/1.0
Project-URL: Bug Tracker, https://github.com/juanretamales/DataframeToDB/issues
Keywords: sqlalchemy,dataframe,to_sql,to_db,pandas
Platform: UNKNOWN
Classifier: Programming Language :: Python :: 3
Classifier: License :: OSI Approved :: GNU General Public License v3 (GPLv3)
Classifier: Operating System :: OS Independent
License-File: LICENSE.md
License-File: LICENSE.txt
Requires-Dist: pandas
Requires-Dist: numpy
Requires-Dist: python-dateutil
Requires-Dist: SQLAlchemy
